speedup/__init__.py
speedup/_version.py
speedup/main.py
speedup/validators.py
speedup/commands/__init__.py
speedup/commands/base.py
speedup/commands/build.py
speedup/commands/run.py
speedup/parsers/__init__.py
speedup/parsers/parser.py
speedup/utils/__init__.py
speedup/utils/error_handling.py
speedup/utils/process_helpers.py
speedup/utils/progress_bar.py
speedup-0.1.dist-info/LICENSE
speedup-0.1.dist-info/METADATA
speedup-0.1.dist-info/WHEEL
speedup-0.1.dist-info/entry_points.txt
speedup-0.1.dist-info/top_level.txt
speedup-0.1.dist-info/RECORD
